databank/__init__.py
databank/core.py
databank/query.py
databank/utils.py
databank-1.1.0.dist-info/METADATA
databank-1.1.0.dist-info/WHEEL
databank-1.1.0.dist-info/licenses/LICENSE
databank-1.1.0.dist-info/RECORD
