Metadata-Version: 2.4
Name: databank
Version: 1.1.0
Summary: Databank is an easy-to-use Python library for making raw SQL queries in a multi-threaded environment.
Author-email: snapADDY GmbH <info@snapaddy.com>
License-File: LICENSE
Requires-Python: >=3.11
Requires-Dist: sqlalchemy>=2.0.4
Provides-Extra: asyncio
Requires-Dist: greenlet>=1; extra == 'asyncio'
